MANIFEST.in
README.rst
setup.cfg
setup.py
pagd/__init__.py
pagd/h.py
pagd/interfaces.py
pagd/lib.py
pagd/script.py
pagd.egg-info/PKG-INFO
pagd.egg-info/SOURCES.txt
pagd.egg-info/dependency_links.txt
pagd.egg-info/entry_points.txt
pagd.egg-info/namespace_packages.txt
pagd.egg-info/not-zip-safe
pagd.egg-info/requires.txt
pagd.egg-info/top_level.txt
pagd/commands/__init__.py
pagd/commands/commands.py
pagd/commands/create.py
pagd/commands/generate.py
pagd/commands/newpage.py
pagd/commands/publish.py
pagd/contents/__init__.py
pagd/contents/native.py
pagd/contents/pandoc.py
pagd/contexts/__init__.py
pagd/contexts/git.py
pagd/contexts/hg.py
pagd/layouts/__init__.py
pagd/layouts/myblog.py
pagd/layouts/myblog/config.json.tmpl
pagd/layouts/myblog/_contents/_context.json.tmpl
pagd/layouts/myblog/_templates/_default.ttl
pagd/layouts/myblog/_templates/_footer.ttl
pagd/layouts/myblog/_templates/_head.ttl
pagd/layouts/myblog/_templates/_header.ttl
pagd/layouts/myblog/_templates/_social.ttl
pagd/layouts/myblog/_templates/index.ttl
pagd/layouts/myblog/_templates/_social/disqus.html
pagd/layouts/myblog/media/myblog.css
pagd/layouts/myblog/media/pygments.css
pagd/layouts/myblog/media/magnific-popup/jquery.magnific-popup.min.js
pagd/layouts/myblog/media/magnific-popup/magnific-popup.css
pagd/rst/__init__.py
pagd/rst/gallery.py
pagd/rst/sourcecode.py
pagd/rst/youtube.py
pagd/templates/__init__.py
pagd/templates/jinja2.py
pagd/templates/mako.py
pagd/templates/tayra.py